text_2_img/__init__.py
text_2_img/image_utils.py
text_2_img-0.0.17.dist-info/LICENSE
text_2_img-0.0.17.dist-info/METADATA
text_2_img-0.0.17.dist-info/WHEEL
text_2_img-0.0.17.dist-info/top_level.txt
text_2_img-0.0.17.dist-info/RECORD
